{
  "blue_dawn": {
    "sounds": [
      {
        "name": "raimudiscsmod:blue_dawn",
        "stream": true
      }
    ]
  },

  "overgrown": {
    "sounds": [
      {
        "name": "raimudiscsmod:overgrown",
        "stream": true
      }
    ]
  },

  "natsukashii": {
    "sounds": [
      {
        "name": "raimudiscsmod:natsukashii",
        "stream": true
      }
    ]
  },

  "kaze_ni_natte": {
    "sounds": [
      {
        "name": "raimudiscsmod:kaze_ni_natte",
        "stream": true
      }
    ]
  },
  "dandelions_lullaby": {
    "sounds": [
      {
        "name": "raimudiscsmod:dandelions_lullaby",
        "stream": true
      }
    ]
  },
  "earth_calling": {
    "sounds": [
      {
        "name": "raimudiscsmod:earth_calling",
        "stream": true
      }
    ]
  },
  "nap_time_in_shibuya": {
    "sounds": [
      {
        "name": "raimudiscsmod:nap_time_in_shibuya",
        "stream": true
      }
    ]
  }
}